edad/__init__.py
edad/edad.py
edad-0.1.dist-info/METADATA
edad-0.1.dist-info/WHEEL
edad-0.1.dist-info/top_level.txt
edad-0.1.dist-info/RECORD
