Metadata-Version: 2.1
Name: edad
Version: 0.1
Summary: Description of your package
Home-page: https://your-package-url.com
Author: Nitin Singh Negi
License: UNKNOWN
Platform: UNKNOWN
Classifier: Programming Language :: Python :: 3
Classifier: License :: OSI Approved :: MIT License
Classifier: Operating System :: OS Independent
Requires-Dist: pandas
